einconv/__init__.py
einconv/conv_index_pattern.py
einconv/utils.py
einconv/expressions/__init__.py
einconv/expressions/convNd_forward.py
einconv/expressions/convNd_input_vjp.py
einconv/expressions/convNd_kfac_reduce.py
einconv/expressions/convNd_kfc.py
einconv/expressions/convNd_unfold.py
einconv/expressions/convNd_weight_vjp.py
einconv/expressions/utils.py
einconv/functionals/__init__.py
einconv/functionals/conv.py
einconv/functionals/unfold.py
einconv/modules/__init__.py
einconv/modules/conv.py
einconv/modules/unfold.py
einconv/simplifications/__init__.py
einconv/simplifications/opt.py
einconv-0.1.0.dist-info/LICENSE.txt
einconv-0.1.0.dist-info/METADATA
einconv-0.1.0.dist-info/WHEEL
einconv-0.1.0.dist-info/top_level.txt
einconv-0.1.0.dist-info/RECORD
